{
  "version": "5.1.1",
  "flags": {},
  "shapes": [
    {
      "description": "",
      "label": "cervical vertebra",
      "points": [
        [
          450.0277777777778,
          72.55555555555557
        ],
        [
          1054.1944444444443,
          997.5555555555557
        ]
      ],
      "group_id": null,
      "shape_type": "rectangle",
      "flags": {}
    },
    {
      "description": "",
      "label": "C2_1",
      "points": [
        [
          730.2083333333334,
          264.0625
        ]
      ],
      "group_id": null,
      "shape_type": "point",
      "flags": {}
    },
    {
      "description": "",
      "label": "C2_2",
      "points": [
        [
          694.2708333333334,
          336.9791666666667
        ]
      ],
      "group_id": null,
      "shape_type": "point",
      "flags": {}
    },
    {
      "description": "",
      "label": "C2_3",
      "points": [
        [
          678.6262626262626,
          344.2727272727273
        ]
      ],
      "group_id": null,
      "shape_type": "point",
      "flags": {}
    },
    {
      "description": "",
      "label": "C2_4",
      "points": [
        [
          573.5757575757576,
          307.90909090909093
        ]
      ],
      "group_id": null,
      "shape_type": "point",
      "flags": {}
    },
    {
      "label": "C3_1",
      "points": [
        [
          564.1308411214953,
          337.38317757009344
        ]
      ],
      "group_id": null,
      "shape_type": "point",
      "flags": {}
    },
    {
      "label": "C3_2",
      "points": [
        [
          662.2616822429907,
          354.2056074766355
        ]
      ],
      "group_id": null,
      "shape_type": "point",
      "flags": {}
    },
    {
      "label": "C3_3",
      "points": [
        [
          677.214953271028,
          383.1775700934579
        ]
      ],
      "group_id": null,
      "shape_type": "point",
      "flags": {}
    },
    {
      "label": "C3_4",
      "points": [
        [
          661.3271028037383,
          439.2523364485981
        ]
      ],
      "group_id": null,
      "shape_type": "point",
      "flags": {}
    },
    {
      "label": "C3_5",
      "points": [
        [
          636.0934579439253,
          455.1401869158878
        ]
      ],
      "group_id": null,
      "shape_type": "point",
      "flags": {}
    },
    {
      "label": "C3_6",
      "points": [
        [
          536.0934579439253,
          437.38317757009344
        ]
      ],
      "group_id": null,
      "shape_type": "point",
      "flags": {}
    },
    {
      "label": "C4_1",
      "points": [
        [
          525.8130841121496,
          468.22429906542055
        ]
      ],
      "group_id": null,
      "shape_type": "point",
      "flags": {}
    },
    {
      "label": "C4_2",
      "points": [
        [
          630.4859813084112,
          471.9626168224299
        ]
      ],
      "group_id": null,
      "shape_type": "point",
      "flags": {}
    },
    {
      "label": "C4_3",
      "points": [
        [
          644.5046728971963,
          494.39252336448595
        ]
      ],
      "group_id": null,
      "shape_type": "point",
      "flags": {}
    },
    {
      "label": "C4_4",
      "points": [
        [
          623.0093457943925,
          565.4205607476636
        ]
      ],
      "group_id": null,
      "shape_type": "point",
      "flags": {}
    },
    {
      "label": "C4_5",
      "points": [
        [
          613.6635514018692,
          571.9626168224298
        ]
      ],
      "group_id": null,
      "shape_type": "point",
      "flags": {}
    },
    {
      "label": "C4_6",
      "points": [
        [
          512.7289719626168,
          573.8317757009346
        ]
      ],
      "group_id": null,
      "shape_type": "point",
      "flags": {}
    },
    {
      "label": "C5_1",
      "points": [
        [
          521.1401869158879,
          611.214953271028
        ]
      ],
      "group_id": null,
      "shape_type": "point",
      "flags": {}
    },
    {
      "label": "C5_2",
      "points": [
        [
          601.5140186915888,
          594.3925233644859
        ]
      ],
      "group_id": null,
      "shape_type": "point",
      "flags": {}
    },
    {
      "label": "C5_3",
      "points": [
        [
          622.0747663551402,
          604.6728971962616
        ]
      ],
      "group_id": null,
      "shape_type": "point",
      "flags": {}
    },
    {
      "label": "C5_4",
      "points": [
        [
          645.4392523364486,
          678.5046728971962
        ]
      ],
      "group_id": null,
      "shape_type": "point",
      "flags": {}
    },
    {
      "label": "C5_5",
      "points": [
        [
          639.8317757009346,
          698.1308411214953
        ]
      ],
      "group_id": null,
      "shape_type": "point",
      "flags": {}
    },
    {
      "label": "C5_6",
      "points": [
        [
          523.0093457943925,
          714.018691588785
        ]
      ],
      "group_id": null,
      "shape_type": "point",
      "flags": {}
    },
    {
      "label": "C6_1",
      "points": [
        [
          531.4205607476636,
          737.3831775700934
        ]
      ],
      "group_id": null,
      "shape_type": "point",
      "flags": {}
    },
    {
      "label": "C6_2",
      "points": [
        [
          622.0747663551402,
          705.607476635514
        ]
      ],
      "group_id": null,
      "shape_type": "point",
      "flags": {}
    },
    {
      "label": "C6_3",
      "points": [
        [
          650.1121495327103,
          728.9719626168223
        ]
      ],
      "group_id": null,
      "shape_type": "point",
      "flags": {}
    },
    {
      "label": "C6_4",
      "points": [
        [
          670.6728971962617,
          784.1121495327102
        ]
      ],
      "group_id": null,
      "shape_type": "point",
      "flags": {}
    },
    {
      "label": "C6_5",
      "points": [
        [
          656.6542056074767,
          807.4766355140187
        ]
      ],
      "group_id": null,
      "shape_type": "point",
      "flags": {}
    },
    {
      "label": "C6_6",
      "points": [
        [
          549.1775700934579,
          836.4485981308411
        ]
      ],
      "group_id": null,
      "shape_type": "point",
      "flags": {}
    },
    {
      "label": "C7_1",
      "points": [
        [
          576.2803738317757,
          869.1588785046729
        ]
      ],
      "group_id": null,
      "shape_type": "point",
      "flags": {}
    },
    {
      "label": "C7_2",
      "points": [
        [
          667.8691588785047,
          820.5607476635514
        ]
      ],
      "group_id": null,
      "shape_type": "point",
      "flags": {}
    },
    {
      "label": "C7_3",
      "points": [
        [
          688.4299065420561,
          830.841121495327
        ]
      ],
      "group_id": null,
      "shape_type": "point",
      "flags": {}
    },
    {
      "label": "C7_4",
      "points": [
        [
          716.4672897196261,
          893.4579439252336
        ]
      ],
      "group_id": null,
      "shape_type": "point",
      "flags": {}
    },
    {
      "label": "C7_5",
      "points": [
        [
          715.5327102803739,
          917.7570093457944
        ]
      ],
      "group_id": null,
      "shape_type": "point",
      "flags": {}
    },
    {
      "label": "C7_6",
      "points": [
        [
          615.5327102803739,
          983.1775700934579
        ]
      ],
      "group_id": null,
      "shape_type": "point",
      "flags": {}
    }
  ],
  "imagePath": "1 (24).JPG",
  "imageData": null,
  "imageHeight": 1334,
  "imageWidth": 1332
}